custCLI/CLI.py
custCLI/__init__.py
custCLI-0.2.2.dist-info/LICENSE
custCLI-0.2.2.dist-info/METADATA
custCLI-0.2.2.dist-info/WHEEL
custCLI-0.2.2.dist-info/top_level.txt
custCLI-0.2.2.dist-info/RECORD
