Metadata-Version: 2.1
Name: custCLI
Version: 0.2.2
Summary: A python library for creating a CLI with custom commands and parameters
Home-page: UNKNOWN
Author: FunMetJoel
License: MIT
Platform: UNKNOWN
Classifier: Intended Audience :: Developers
Classifier: License :: OSI Approved :: MIT License
Classifier: Programming Language :: Python
Classifier: Programming Language :: Python :: 3
Classifier: Operating System :: OS Independent
